{
"type": "FeatureCollection",
"crs": { "type": "name", "properties": { "name": "urn:ogc:def:crs:OGC:1.3:CRS84" } },
"features": [
{ "type": "Feature", "properties": { "種別": "保健センター", "名称": "大井保健センター", "住所": "東京都品川区大井2-27-20", "電話番号": "03-3772-2666", "経度": 139.7303, "緯度": 35.60418 }, "geometry": { "type": "Point", "coordinates": [ 139.7303, 35.60418 ] } }
]
}
