{
"type": "FeatureCollection",
"crs": { "type": "name", "properties": { "name": "urn:ogc:def:crs:OGC:1.3:CRS84" } },
"features": [
{ "type": "Feature", "properties": { "種別": "保健センター", "名称": "荏原保健センター", "住所": "東京都品川区荏原2-9-6 ", "電話番号": "03-3788-2000", "LocName": "東京都\/品川区\/荏原\/二丁目\/９番", "fX": 139.71111, "fY": 35.61701, "iConf": 5, "iLvl": 7 }, "geometry": { "type": "Point", "coordinates": [ 139.71111, 35.61701 ] } },
{ "type": "Feature", "properties": { "種別": "保健センター", "名称": "品川保健センター", "住所": "東京都品川区北品川3-11-22", "電話番号": "03-3474-2000", "LocName": "東京都\/品川区\/北品川\/三丁目\/１１番", "fX": 139.73927, "fY": 35.61644, "iConf": 5, "iLvl": 7 }, "geometry": { "type": "Point", "coordinates": [ 139.73927, 35.61644 ] } },
{ "type": "Feature", "properties": { "種別": "保健センター", "名称": "大井保健センター", "住所": "東京都品川区大井2-27-20 ", "電話番号": "03-3772-2666", "LocName": "東京都\/品川区\/大井\/二丁目\/２７番", "fX": 139.73032, "fY": 35.60418, "iConf": 5, "iLvl": 7 }, "geometry": { "type": "Point", "coordinates": [ 139.73032, 35.60418 ] } }
]
}
